LICENSE
README.md
setup.py
eegpy/__init__.py
eegpy.egg-info/PKG-INFO
eegpy.egg-info/SOURCES.txt
eegpy.egg-info/dependency_links.txt
eegpy.egg-info/requires.txt
eegpy.egg-info/top_level.txt
eegpy/analysis/__init__.py
eegpy/analysis/corelation_analysis.py
eegpy/analysis/power_spectrum.py
eegpy/analysis/stats_analysis.py
eegpy/analysis/time_frequency.py
eegpy/cognitive_analysis_module/__init__.py
eegpy/cognitive_analysis_module/cognitive_comparision.py
eegpy/cognitive_analysis_module/cognitive_indexes.py
eegpy/comparitive_analysis/__init__.py
eegpy/data/__init__.py
eegpy/data/csv.py
eegpy/data/mff.py
eegpy/data/task2.py
eegpy/data/xlsx.py
eegpy/preprocessing/__init__.py
eegpy/preprocessing/epoching.py
eegpy/preprocessing/filtering.py
eegpy/utils/__init__.py
eegpy/utils/data.py
eegpy/utils/performance_eval.py
eegpy/visualization/__init__.py
eegpy/visualization/plot_cluster.py
eegpy/visualization/plot_coherence.py
eegpy/visualization/plot_cross-correlation.py
eegpy/visualization/plot_eeg_signal.py
eegpy/visualization/plot_heatmap.py
eegpy/visualization/plot_power_spectrum.py
eegpy/visualization/plot_spectogram.py
eegpy/visualization/plot_time_series.py
eegpy/visualization/plot_topomap.py